{
  "url": "https://www.tempo.co/politik/icw-temukan-28-yayasan-mbg-terafiliasi-dengan-partai-politik-2092889",
  "title": "ICW Temukan 28 Yayasan MBG Terafiliasi dengan Partai Politik",
  "date": "2026-04-11",
  "content": "INDONESIACorruption Watch(ICW) menemukan ada 28 yayasan mitra makan bergizi gratis atauMBGyang terafiliasi dengan partai politik. Peneliti ICW, Seira Tamara, mengatakan 28 yayasan ini merupakan hasil pantauan terhadap 102 yayasan pengelola Satuan Pelayanan Pemenuhan Gizi (SPPG) yang dilakukan ICW secara acak pada periode Oktober-November 2025 dari seluruh Indonesia.\n“Ketika berbicara soal individunya itu ada sekitar 43. Kenapa individunya jumlahnya lebih banyak? Karena di satu yayasan itu bisa jadi ada lebih dari satu individu yang punya afiliasi terhadap partai politik,” kata Seira di kantor ICW, Jakarta, Selasa, 25 November 2025.\nSeira mengatakan afiliasi yayasan dengan parpol ini ditandai kepemilikan yayasan oleh pengurus parpol, anggota partai, atau anggota yayasan yang pernah diusung oleh partai politik tertentu dalam kontestasi pemilihan legislatif nasional maupun daerah.\n“Partai Gerindra, partai yang juga didirikan oleh Presiden Prabowo adalah partai dengan jumlah terbanyak yang punya afiliasi di yayasan kepemilikan SPPG,” ujar Seira.\nYayasan yang terafiliasi Partai Gerindra berjumlah 7 yayasan, Partai Keadilan Sejahtera berjumlah 5 yayasan, Partai Amanat Nasional ada 4, PDIP 3 yayasan, NasDem 3 yayasan, Partai Solidaritas Indonesia 2 yayasan, Partai Berkarya 2, Hanura 2. Sedangkan, Partai Persatuan Pembangunan, Partai Kebangkitan Bangsa, Partai Bulan Bintang, Partai Demokrat, dan Partai Swara Rakyat Indonesia, masing-masing memiliki afiliasi satu yayasan.\nICW mencatat, dari total 43 individu yayasan mitra MBG yang terafilias partai politik, 4 di antaranya merupakan anggota DPR RI atau DPRD aktif.\nSeira mengatakan data yayasan yang dipantau ICW diperoleh dari lama resmi Direktorat Jenderal Administrasi Hukum Umum Kementerian Hukum. Sedangkan, individu yang terafiliasi partai politik ditelusuri tercantum dalam struktur resmi yayasan.\nCatatan: Artikel ini mengalami perubahan di judul pada pukul 25 November 2025 pukul 14.35 WIB . Sebelumnya tertulis jumlah yayasan yang terafiliasi 27 dan diubah menjadi 28 setelah ada keterangan susulan dari ICW.",
  "source": "Tempo.co",
  "scraped_at": "2026-04-11T14:45:52.783561",
  "status": "cleaned"
}